errors.py
oas_yaml_combine.py
vendor/liboasyamlcombine.so
oas_yaml_combine_py-0.0.2.dist-info/METADATA
oas_yaml_combine_py-0.0.2.dist-info/WHEEL
oas_yaml_combine_py-0.0.2.dist-info/licenses/LICENSE
oas_yaml_combine_py-0.0.2.dist-info/RECORD
