Metadata-Version: 2.4
Name: oas-yaml-combine-py
Version: 0.0.2
Summary: A python wrapper over a dynamic library build of oas_yaml_combine from openapi-utils
Project-URL: Homepage, https://github.com/sarpt/oas-yaml-combine-py
Project-URL: Issues, https://github.com/sarpt/oas-yaml-combine-py/issues
Author-email: sarpt <sarpt.contact@gmail.com>
License-File: LICENSE
Classifier: License :: OSI Approved :: MIT License
Classifier: Operating System :: POSIX
Classifier: Operating System :: Unix
Classifier: Programming Language :: Python :: 3
Requires-Python: >=3.8
